{
  "$schema": "https://developer.microsoft.com/json-schemas/fabric/item/report/definition/visualContainer/2.10.0/schema.json",
  "name": "0000000000000000000b",
  "position": {
    "x": 728,
    "y": 76,
    "z": 1011,
    "height": 112,
    "width": 528,
    "tabOrder": 1011
  },
  "visual": {
    "visualType": "cardVisual",
    "query": {
      "queryState": {
        "Data": {
          "projections": [
            {
              "field": {
                "Measure": {
                  "Expression": {
                    "SourceRef": {
                      "Entity": "CSD"
                    }
                  },
                  "Property": "Number of CSDs"
                }
              },
              "queryRef": "CSD.Number of CSDs",
              "nativeQueryRef": "Number of CSDs"
            },
            {
              "field": {
                "Measure": {
                  "Expression": {
                    "SourceRef": {
                      "Entity": "CSD"
                    }
                  },
                  "Property": "CSD Children 0 to 5"
                }
              },
              "queryRef": "CSD.CSD Children 0 to 5",
              "nativeQueryRef": "CSD Children 0 to 5"
            },
            {
              "field": {
                "Measure": {
                  "Expression": {
                    "SourceRef": {
                      "Entity": "CSD"
                    }
                  },
                  "Property": "CSD Indicator Children"
                }
              },
              "queryRef": "CSD.CSD Indicator Children",
              "nativeQueryRef": "CSD Indicator Children"
            },
            {
              "field": {
                "Measure": {
                  "Expression": {
                    "SourceRef": {
                      "Entity": "CSD"
                    }
                  },
                  "Property": "CSD Indicator Rate"
                }
              },
              "queryRef": "CSD.CSD Indicator Rate",
              "nativeQueryRef": "CSD Indicator Rate"
            }
          ]
        }
      }
    },
    "objects": {
      "outline": [
        {
          "properties": {
            "show": {
              "expr": {
                "Literal": {
                  "Value": "false"
                }
              }
            }
          },
          "selector": {
            "id": "default"
          }
        }
      ],
      "value": [
        {
          "properties": {
            "fontSize": {
              "expr": {
                "Literal": {
                  "Value": "32D"
                }
              }
            },
            "fontColor": {
              "solid": {
                "color": {
                  "expr": {
                    "Literal": {
                      "Value": "'#102A43'"
                    }
                  }
                }
              }
            }
          },
          "selector": {
            "id": "default"
          }
        }
      ],
      "label": [
        {
          "properties": {
            "show": {
              "expr": {
                "Literal": {
                  "Value": "true"
                }
              }
            },
            "fontSize": {
              "expr": {
                "Literal": {
                  "Value": "10D"
                }
              }
            },
            "fontColor": {
              "solid": {
                "color": {
                  "expr": {
                    "Literal": {
                      "Value": "'#52606D'"
                    }
                  }
                }
              }
            }
          },
          "selector": {
            "id": "default"
          }
        }
      ],
      "cardCalloutArea": [
        {
          "properties": {
            "show": {
              "expr": {
                "Literal": {
                  "Value": "true"
                }
              }
            },
            "paddingUniform": {
              "expr": {
                "Literal": {
                  "Value": "8L"
                }
              }
            },
            "backgroundFillColor": {
              "solid": {
                "color": {
                  "expr": {
                    "Literal": {
                      "Value": "'#FFFFFF'"
                    }
                  }
                }
              }
            },
            "backgroundTransparency": {
              "expr": {
                "Literal": {
                  "Value": "0D"
                }
              }
            }
          }
        }
      ]
    },
    "visualContainerObjects": {
      "background": [
        {
          "properties": {
            "show": {
              "expr": {
                "Literal": {
                  "Value": "true"
                }
              }
            },
            "color": {
              "solid": {
                "color": {
                  "expr": {
                    "Literal": {
                      "Value": "'#FFFFFF'"
                    }
                  }
                }
              }
            },
            "transparency": {
              "expr": {
                "Literal": {
                  "Value": "0D"
                }
              }
            }
          }
        }
      ],
      "border": [
        {
          "properties": {
            "show": {
              "expr": {
                "Literal": {
                  "Value": "true"
                }
              }
            },
            "color": {
              "solid": {
                "color": {
                  "expr": {
                    "Literal": {
                      "Value": "'#D9E2EC'"
                    }
                  }
                }
              }
            },
            "radius": {
              "expr": {
                "Literal": {
                  "Value": "6D"
                }
              }
            }
          }
        }
      ],
      "padding": [
        {
          "properties": {
            "top": {
              "expr": {
                "Literal": {
                  "Value": "6D"
                }
              }
            },
            "bottom": {
              "expr": {
                "Literal": {
                  "Value": "6D"
                }
              }
            },
            "left": {
              "expr": {
                "Literal": {
                  "Value": "8D"
                }
              }
            },
            "right": {
              "expr": {
                "Literal": {
                  "Value": "8D"
                }
              }
            }
          }
        }
      ]
    }
  }
}